Workbook

Sheet Feature List
A1: MRI ERP Implementation Taxonomy — Feature List & QA Tracker
A2: Existing functionality (from source) + items folded in from the DevOps board. DevOps Ref maps each feature to its story. See Comparison sheet for the full reconciliation.
A4: # | B4: Category | C4: Feature | D4: Description | E4: Where it lives | F4: Source | G4: Dev Status | H4: Tested? | I4: QA Status | J4: DevOps Ref | K4: QA Notes
A5: 1 | B5: Views & Navigation | C5: Three top-level views | D5: Switch between Business Process (default), System (MRI PMX), and Mapping (coverage matrix) views via the view switcher. | E5: main.js · switchView() | F5: Existing | G5: Done | H5: No | I5: Not Tested | J5: 3216
A6: 2 | B6: Views & Navigation | C6: View-specific hints | D6: Contextual sub-heading explains what each view shows as you switch. | E6: main.js · VIEW_HINTS | F6: Existing | G6: Done | H6: No | I6: Not Tested | J6: 3278
A7: 3 | B7: Views & Navigation | C7: Module tab bar | D7: Tab per MRI module in the System view; active tab is highlighted; clicking switches modules. | E7: main.js · switchTab() / index.html | F7: Existing | G7: Done | H7: Yes | I7: Pass | J7: 3218, 3228 | K7: Tested and closed 15 Sept 2026.
A8: 4 | B8: Views & Navigation | C8: Value-stream tab bar | D8: Tab per business value stream in the Business view, with supporting streams visually marked. | E8: businessView.js · renderBusinessTabs() | F8: Existing | G8: Done | H8: No | I8: Not Tested | J8: 3221
A9: 5 | B9: Views & Navigation | C9: Detail panel | D9: Right-side slide-in panel opens on any process/sub click, showing full detail for that item. | E9: panel.js / businessView.js | F9: Existing | G9: Done | H9: No | I9: Not Tested | J9: 3217
A10: 6 | B10: Views & Navigation | C10: Expand / collapse sub-processes | D10: Processes with sub-processes can be expanded individually or all at once (System view). | E10: main.js · toggleExpandAll() | F10: Existing | G10: Done | H10: No | I10: Not Tested | J10: 3219
A11: 7 | B11: Views & Navigation | C11: Keyboard shortcuts | D11: Esc closes any modal/panel; Enter confirms add dialogs; Ctrl/Cmd+Enter saves the edit modal. | E11: main.js · keydown handler | F11: Existing | G11: Done | H11: No | I11: Not Tested | J11: 3279
A12: 8 | B12: System (MRI PMX) View | C12: Process/sub card grid | D12: Columns of process and sub-process cards for the active MRI module. | E12: grid.js | F12: Existing | G12: Done | H12: Yes | I12: Pass | J12: 3218, 3228 | K12: Tested and closed 15 Sept 2026.
A13: 9 | B13: System (MRI PMX) View | C13: MRI module reference | D13: Panel shows the MRI navigation path (mri_title) for the process. | E13: panel.js | F13: Existing | G13: Done | H13: No | I13: Not Tested | J13: 3229
A14: 10 | B14: System (MRI PMX) View | C14: Setup prerequisites | D14: Panel lists MRI configuration that must exist before the process can run (mri_prereqs). | E14: panel.js | F14: Existing | G14: Done | H14: No | I14: Not Tested | J14: 3229
A15: 11 | B15: System (MRI PMX) View | C15: Associated MRI screens | D15: Panel lists supporting MRI screens with per-screen descriptions (mri_assoc). | E15: panel.js | F15: Existing | G15: Done | H15: No | I15: Not Tested | J15: 3229
A16: 12 | B16: System (MRI PMX) View | C16: Core activities & overview | D16: Business description and the activities a person performs for each process. | E16: panel.js | F16: Existing | G16: Done | H16: No | I16: Not Tested | J16: 3217, 3229
A17: 13 | B17: System (MRI PMX) View | C17: 9 built-in MRI modules | D17: CM, GL, AP, RM, Job Cost, Corporate AR, Budgeting & Forecasting, Investment Accounting, Fixed Asset Accounting. | E17: data/index.js | F17: Existing | G17: Done | H17: Yes | I17: Pass | J17: 3228 | K17: Tested and closed 15 Sept 2026.
A18: 14 | B18: Business Process View | C18: CRE value-stream taxonomy | D18: Business view organised as Level-1 value streams → Level-2 groups → Level-3 process cards. | E18: business/index.js · valueStreams.js | F18: Existing | G18: Done | H18: No | I18: Not Tested | J18: 3221
A19: 15 | B19: Business Process View | C19: Market variation detail | D19: Per-item guidance that differs by market (UK, US, Pan-European), shown for the selected markets. | E19: businessView.js · showBusinessPanel() | F19: Existing | G19: Done | H19: No | I19: Not Tested | J19: 3223
A20: 16 | B20: Business Process View | C20: Vertical / sector detail | D20: Colour-tagged per-sector guidance (Retail, Industrial, Office, Residential). | E20: businessView.js | F20: Existing | G20: Done | H20: No | I20: Not Tested | J20: 3224
A21: 17 | B21: Business Process View | C21: Standards & frameworks chips | D21: Regulatory/standards tags on cards and in the panel signal compliance weight. | E21: businessView.js | F21: Existing | G21: Done | H21: No | I21: Not Tested | J21: 3225
A22: 18 | B22: Business Process View | C22: Market filter | D22: Multi-select filter drives which market-variation blocks appear in the panel. | E22: businessView.js · renderBusinessFilters() | F22: Existing | G22: Done | H22: No | I22: Not Tested | J22: 3226
A23: 19 | B23: Business Process View | C23: Vertical filter | D23: Multi-select filter hides cards not relevant to the chosen sectors. | E23: businessView.js · matchesVerticals() | F23: Existing | G23: Done | H23: No | I23: Not Tested | J23: 3227
A24: 20 | B24: Business Process View | C24: System-coverage filter | D24: Filter cards by coverage tag (Full / Partial / Outside / Untagged). | E24: businessView.js · matchesCoverage() | F24: Existing | G24: Done | H24: No | I24: Not Tested | J24: 3241
A25: 21 | B25: Business Process View | C25: Enrichment flag | D25: Cards seeded from the reference guide are flagged as needing Market/Vertical/Standards detail. | E25: business/index.js · needsEnrichment (data flag); businessView.js renders it | F25: Existing | G25: Done | H25: No | I25: Not Tested | J25: 3222
A26: 22 | B26: Business Process View | C26: Value-stream context | D26: Panel shows the parent value stream, its note, and whether it is a supporting stream. | E26: businessView.js | F26: Existing | G26: Done | H26: No | I26: Not Tested | J26: 3221
A27: 23 | B27: Mapping / Coverage View | C27: Coverage matrix | D27: Matrix of business domains (rows) × system modules (columns) with per-cell link counts. | E27: mappingView.js · renderMapping() | F27: Existing | G27: Done | H27: No | I27: Not Tested | J27: 3235
A28: 24 | B28: Mapping / Coverage View | C28: Gap highlighting | D28: Domains with no system links are flagged as unmapped; coverage stats summarise the matrix. | E28: mappingView.js / links.js | F28: Existing | G28: Done | H28: No | I28: Not Tested | J28: 3237
A29: 25 | B29: Mapping / Coverage View | C29: Cell detail (visual flow) | D29: Clicking a cell opens a business→system flow list of the linked process pairs. | E29: mappingView.js · showCell() | F29: Existing | G29: Done | H29: Yes | I29: Pass | J29: 3236 | K29: Tested 2026-08-18
A30: 26 | B30: Mapping / Coverage View | C30: Coverage colour coding | D30: Cells and chips colour-coded by coverage (Full / Partial / Outside; mixed shown distinctly). | E30: mappingView.js · cellCoverage() | F30: Existing | G30: Done | H30: No | I30: Not Tested | J30: 3235, 3239
A31: 27 | B31: Mapping / Coverage View | C31: Click-through navigation | D31: From a cell flow, jump straight to the business or system item in its own view. | E31: mappingView.js / main.js · navigateToLinked() | F31: Existing | G31: Done | H31: Yes | I31: Pass | J31: 3232, 3236 | K31: Tested 2026-08-18
A32: 28 | B32: Edit Mode | C32: Toggle edit mode | D32: Enter/exit Edit Mode to reveal add/remove/edit controls across the grid. | E32: main.js · toggleEdit() | F32: Existing | G32: Done | H32: No | I32: Not Tested | J32: 3247, 3248
A33: 29 | B33: Edit Mode | C33: Add column / domain | D33: Add a new column (System) or domain (Business). | E33: addModal.js / businessView.js | F33: Existing | G33: Done | H33: No | I33: Not Tested | J33: 3247, 3248
A34: 30 | B34: Edit Mode | C34: Add process / sub-process | D34: Add processes and sub-processes inline; new items open for editing. | E34: addModal.js / businessView.js | F34: Existing | G34: Done | H34: No | I34: Not Tested | J34: 3247, 3248
A35: 31 | B35: Edit Mode | C35: Edit any item field | D35: In-place modal edits title, description, activities, MRI fields, and client note. | E35: editModal.js / businessEditModal.js | F35: Existing | G35: Done | H35: No | I35: Not Tested | J35: 3247, 3248
A36: 32 | B36: Edit Mode | C36: Remove items | D36: Delete columns, processes, and sub-processes (with undo). | E36: main.js · removeItem() / businessRemove() | F36: Existing | G36: Done | H36: No | I36: Not Tested | J36: 3247, 3248
A37: 33 | B37: Edit Mode | C37: Add custom module tab | D37: Create a new custom module tab with its own name, icon, and header colour. | E37: addModal.js · confirmAddTab() | F37: Existing | G37: Done | H37: No | I37: Not Tested | J37: 3276
A38: 34 | B38: Scope & Coverage Tagging | C38: Scope tags (System) | D38: Tag each item Core / Custom / Out-of-Scope by cycling; drives filtering and export. | E38: main.js · cycleScope() | F38: Existing | G38: Done | H38: No | I38: Not Tested | J38: 3243
A39: 35 | B39: Scope & Coverage Tagging | C39: Bulk-tag column scope | D39: Set scope for every process/sub in a column at once. | E39: main.js · bulkTagColumn() | F39: Existing | G39: Done | H39: No | I39: Not Tested | J39: 3245
A40: 36 | B40: Scope & Coverage Tagging | C40: Scope filter (System) | D40: Multi-select filter shows only selected scopes (Core/Custom/OOS/Untagged). | E40: main.js · renderScopeFilter() | F40: Existing | G40: Done | H40: No | I40: Not Tested | J40: 3246
A41: 37 | B41: Scope & Coverage Tagging | C41: Auto out-of-scope | D41: Items not linked to any value stream can be treated as auto out-of-scope. | E41: grid.js · effectiveScope() | F41: Existing | G41: Done | H41: No | I41: Not Tested | J41: 3244
A42: 38 | B42: Scope & Coverage Tagging | C42: Coverage tags (Business) | D42: Tag business processes Full / Partial / Outside for system coverage; bulk-tag per domain. | E42: businessView.js · cycleCoverage()/bulkTagCoverage() | F42: Existing | G42: Done | H42: No | I42: Not Tested | J42: 3238, 3242
A43: 39 | B43: Scope & Coverage Tagging | C43: Missing-link warning | D43: Full/Partial items with no system link are flagged with a "link needed" warning. | E43: businessView.js · coverageNeedsLink() | F43: Existing | G43: Done | H43: No | I43: Not Tested | J43: 3240
A44: 40 | B44: Cross-view Linkage | C44: Business ⇄ system links | D44: Each business process links to the MRI PMX process(es) that deliver it, with a coverage level. | E44: links.js | F44: Existing | G44: Done | H44: Yes | I44: Pass | J44: 3231, 3233 | K44: Tested 2026-08-18
A45: 41 | B45: Cross-view Linkage | C45: Seed link template | D45: Group-level seed mapping expands to per-process links at load; refined per client. | E45: links.js · SEED_LINKS / GROUP_LINKS | F45: Existing | G45: Done | H45: Yes | I45: Pass | J45: 3231 | K45: Tested 2026-08-18
A46: 42 | B46: Cross-view Linkage | C46: Panel cross-references | D46: Both panels show the linked items on the other side, navigable with one click. | E46: main.js · renderLinkSection() | F46: Existing | G46: Done | H46: Yes | I46: Pass | J46: 3231 | K46: Tested 2026-08-18
A47: 43 | B47: Cross-view Linkage | C47: Inline link editor | D47: Edit-mode mapping cards let you add/remove links and set coverage per process. | E47: mappingView.js · buildDomainCard() | F47: Existing | G47: Done | H47: No | I47: Not Tested | J47: 3233, 3234
A48: 44 | B48: Cross-view Linkage | C48: Add-link drill-down combobox | D48: Searchable 3-step picker (Module → Process → Sub-process) to add a system link. | E48: mappingView.js · openComboDropdown() | F48: Existing | G48: Done | H48: No | I48: Not Tested | J48: 3233
A49: 45 | B49: Versioning & Persistence | C49: Save named versions | D49: Save the full taxonomy state as a named, client-specific version. | E49: versions.js / main.js · confirmSaveAs() | F49: Existing | G49: Done | H49: Yes | I49: Pass | J49: 3250 | K49: Tested and closed 15 Sept 2026.
A50: 46 | B50: Versioning & Persistence | C50: Load / rename / delete versions | D50: Manage saved versions from the Versions side panel. | E50: versionMenu.js / versions.js | F50: Existing | G50: Done | H50: Yes | I50: Pass | J50: 3251 | K50: Tested 2026-08-18
A51: 47 | B51: Versioning & Persistence | C51: Save changes to active version | D51: Overwrite the active version in place while editing. | E51: main.js · saveChangesToVersion() | F51: Existing | G51: Done | H51: No | I51: Not Tested | J51: 3277
A52: 48 | B52: Versioning & Persistence | C52: localStorage persistence | D52: Versions persist in the browser localStorage (per browser/machine). | E52: versions.js | F52: Existing | G52: Done | H52: Yes | I52: Pass | J52: 3250 | K52: Tested and closed 15 Sept 2026.
A53: 49 | B53: Versioning & Persistence | C53: Full-state snapshots | D53: A version captures data, custom modules, module visibility, links, and business data. | E53: main.js / versions.js | F53: Existing | G53: Done | H53: Yes | I53: Pass | J53: 3250 | K53: Tested and closed 15 Sept 2026.
A54: 50 | B54: Versioning & Persistence | C54: Version badge + dirty indicator | D54: Topbar badge shows the active version and an unsaved-changes dot. | E54: main.js · updateVersionBadge() | F54: Existing | G54: Done | H54: No | I54: Not Tested | J54: 3280
A55: 51 | B55: Undo & Reset | C55: Undo (up to 20 steps) | D55: View-aware undo restores the correct module/view before each mutation. | E55: state.js · snapshot() / main.js · undo() | F55: Existing | G55: Done | H55: No | I55: Not Tested | J55: 3252
A56: 52 | B56: Undo & Reset | C56: Reset current tab | D56: Restore the active module (System or Business) to its factory baseline. | E56: main.js · resetTab() | F56: Existing | G56: Done | H56: No | I56: Not Tested | J56: 3253
A57: 53 | B57: Undo & Reset | C57: Reset all | D57: Restore every built-in module to original content. | E57: main.js · resetAll() | F57: Existing | G57: Done | H57: No | I57: Not Tested | J57: 3253
A58: 54 | B58: Module Management | C58: Per-module visibility | D58: Show/hide module tabs; hidden modules are excluded from tabs and export. | E58: main.js · toggleModuleVisible() | F58: Existing | G58: Done | H58: No | I58: Not Tested | J58: 3254 | K58: Board 3254 also mentions per-stream visibility, which is not separately implemented.
A59: 55 | B59: Module Management | C59: Visibility saved per version | D59: Each client version remembers which modules are visible. | E59: main.js / versions.js | F59: Existing | G59: Done | H59: No | I59: Not Tested | J59: 3254
A60: 56 | B60: Module Management | C60: Auto-switch on hide | D60: Hiding the active module moves to the first visible one. | E60: main.js · applyModuleVisibility() | F60: Existing | G60: Done | H60: No | I60: Not Tested | J60: 3254
A61: 57 | B61: Document Export | C61: Generate preview | D61: Build an in-app document preview from the current view and options. | E61: genModal.js · buildDoc() / buildBusinessPreview() | F61: Existing | G61: Done | H61: No | I61: Not Tested | J61: 3255, 3256
A62: 58 | B62: Document Export | C62: Word export (.docx) | D62: Download a branded Open Box .docx (System or Business content), generated with the docx library. | E62: genModal.js · downloadWord() → docxExport.js · generateDocx(); house style from obDocStyle.js | F62: Existing | G62: Done | H62: No | I62: Not Tested | J62: 3255
A63: 59 | B63: Document Export | C63: PDF export (print) | D63: Open a print-ready styled page for Save-as-PDF. | E63: genModal.js · downloadPDF(); house style from obDocStyle.js · houseStyleCSS() | F63: Existing | G63: Done | H63: No | I63: Not Tested | J63: 3256
A64: 60 | B64: Document Export | C64: Content section toggles | D64: Choose to include overview, activities, prerequisites, and associated screens. | E64: genModal.js · buildDoc(); docxExport.js · processBlock() | F64: Existing | G64: Done | H64: No | I64: Not Tested | J64: 3255
A65: 61 | B65: Document Export | C65: Scope include filters | D65: Include/exclude Core, Custom, Out-of-Scope, and Untagged items in the document. | E65: genModal.js · getScopeIncludes(); docxExport.js · scopePass() | F65: Existing | G65: Done | H65: No | I65: Not Tested | J65: 3255
A66: 62 | B66: Document Export | C66: Scope summary table | D66: Document opens with a table of process counts per scope (total vs included). | E66: genModal.js · buildScopeSummary(); docxExport.js · generateDocx() | F66: Existing | G66: Done | H66: No | I66: Not Tested | J66: 3255
A67: 63 | B67: Document Export | C67: Current-tab or all-modules scope | D67: Export just the active module or all visible modules. | E67: genModal.js · getDocTabs() / businessDocTabs() | F67: Existing | G67: Done | H67: No | I67: Not Tested | J67: 3255
A68: 64 | B68: Document Export | C68: Business document mode | D68: Business view exports overview/activities plus market variations, vertical detail, and standards. | E68: docxExport.js · generateBusinessDocx(); genModal.js · buildBusinessPreview() | F68: Existing | G68: Done | H68: No | I68: Not Tested | J68: 3255
A69: 65 | B69: Detail Content | C69: Client notes | D69: Per-item free-text client note, editable in Edit Mode, shown in the panel and saved per version. | E69: clientNote.js / businessEditModal.js | F69: Existing | G69: Done | H69: Yes | I69: Pass | J69: 3249 | K69: Tested and closed 15 Sept 2026.
A70: 66 | B70: Detail Content | C70: Scope / coverage badges | D70: Panel badges show item type, MRI/Business origin, and scope/coverage status. | E70: panel.js / businessView.js | F70: Existing | G70: Done | H70: No | I70: Not Tested | J70: 3217, 3229
A71: 67 | B71: Views & Navigation | C71: Scroll a long tab bar | D71: Tab bar scrolls horizontally when tabs exceed the viewport width so every module/stream stays reachable. | E71: main.css · .tab-bar (overflow-x) | F71: DevOps Backlog | G71: Done | H71: Yes | I71: Pass | J71: 3220 | K71: Implemented in CSS; was absent from the original feature list. | Tested 2026-08-18
A72: 68 | B72: System (MRI PMX) View | C72: Placeholder modules flagged (awaiting SME review) | D72: Visibly flag provisional modules (Job Cost, Corporate AR, Budgeting & Forecasting) as awaiting SME review so provisional content is not presented as final. | E72: — not yet implemented | F72: DevOps Backlog | G72: Not Started | H72: No | I72: Not Tested | J72: 3230 | K72: GAP: data files carry SME-review code comments, but there is no in-app flag.
A73: 69 | B73: Multi-ERP (future) | C73: Select the target ERP | D73: Choose which ERP the System view + link set maps against, so the same business processes can map to different ERPs. | E73: — not implemented (future) | F73: DevOps Backlog | G73: Not Started | H73: N/A | I73: Not Tested | J73: 3257 | K73: MoSCoW: Won’t (future). Single ALL_DATA today.
A74: 70 | B74: Versioning & Persistence | C74: Share a client version between users (export/import) | D74: Export a saved version to a portable file and import it on another machine/teammate to recreate it faithfully. | E74: — not implemented (future) | F74: DevOps Backlog | G74: Not Started | H74: N/A | I74: Not Tested | J74: 3258 | K74: MoSCoW: Won’t (future). CLAUDE.md confirms not built.
A75: 71 | B75: Business Process View | C75: Value-stream naming conventions with descriptions | D75: Ensure each value stream has a clear, standardised naming convention accompanied by a description that explains its scope and purpose. | E75: business/valueStreams.js · VALUE_STREAMS (label + note per stream; title + note per L2 group) | F75: New Requirement | G75: Done | H75: Yes | I75: Pass | J75: 3270 | K75: Story 3270 under Feature 3197 (CRE Powered Value Streams Taxonomy). Tested 2026-08-18. Confirmed Done 2026-09-14 — every value stream carries a label and a note, every L2 group a title and a note.
A76: 72 | B76: Business Process View | C76: Cross-market value-stream validation (US / UK) | D76: Confirm that value-stream names and structures are meaningful for both US and UK markets — e.g. "Recoveries" (UK) vs "Service Charges" (US) — and reconcile terminology where they diverge. | E76: — not yet implemented | F76: New Requirement | G76: Not Started | H76: N/A | I76: Not Tested | J76: 3271 | K76: Story 3271 under Feature 3197 (CRE Powered Value Streams Taxonomy). Board New as at 2026-09-15.
A77: 73 | B77: Scope & Coverage Tagging | C77: Tagging methodology review and taxonomy alignment | D77: Review current scope and coverage tagging to confirm the most appropriate approach, including whether tags should align with the existing taxonomy structure or follow a separate scheme. | E77: — not yet implemented | F77: New Requirement | G77: Not Started | H77: N/A | I77: Not Tested | J77: 3272 | K77: Story 3272 under Feature 3205 (Item-Level System Coverage Tag). Board New as at 2026-09-15.
A78: 74 | B78: Security & Access Control | C78: Security features and responsibility boundaries | D78: Define who can change or edit the master copy, whether access should grant editing rights, and the responsibility boundaries between roles (e.g. consultant vs client vs admin). | E78: — not yet implemented | F78: New Requirement | G78: Not Started | H78: N/A | I78: Not Tested | J78: 3273 | K78: Story 3273 under Feature 3269 (Security & Access Control). Board New as at 2026-09-15.
A79: 75 | B79: Versioning & Persistence | C79: Database persistence (replace localStorage) | D79: Move version and taxonomy data from browser localStorage to a database backend so that data persists across browsers, machines, and users. | E79: — not yet implemented | F79: New Requirement | G79: Not Started | H79: N/A | I79: Not Tested | J79: 3274 | K79: Story 3274 under Feature 3211 (Client Versions). Board New as at 2026-09-15.
A80: 76 | B80: Versioning & Persistence | C80: Version comparison (side-by-side diff) | D80: Side-by-side diff between two saved versions to see what changed from the baseline when tailoring for a client. | E80: — not yet implemented | F80: Nice to Have | G80: Not Started | H80: N/A | I80: Ready for Testing | J80: 3281 | K80: Future enhancement. Story 3281 under Feature 3211 (Client Versions). | Development complete, ready for testing.
A81: 77 | B81: Views & Navigation | C81: Guided discovery workflow | D81: Checklist or wizard walking a consultant through module selection, scope tagging, coverage mapping, and export. | E81: — not in the codebase yet (board: Active, 13 pts) | F81: Nice to Have | G81: In Progress | H81: N/A | I81: Not Tested | J81: 3282 | K81: Story 3282 under Feature 3195 (View Switcher & Shared Shell). Board state Active (13 pts) as at 2026-09-15 — work started; nothing in the codebase yet.
A82: 78 | B82: Versioning & Persistence | C82: Duplicate a version | D82: Clone an existing client version as a starting point for a similar client. | E82: versionMenu.js · startDuplicate(); versions.js · duplicateVersion() | F82: Nice to Have | G82: Done | H82: Yes | I82: Pass | J82: 3283 | K82: Story 3283 under Feature 3211 (Client Versions). Tested 2026-08-18. Confirmed Done 2026-09-14 — Duplicate control on each card in the Versions panel.
A83: 79 | B83: Document Export | C83: Richer export templates | D83: Branded documents with cover page, table of contents, and executive summary. Cover page and TOC delivered; executive summary outstanding. | E83: docxExport.js · buildBrandedDocument() (cover + TOC) — executive summary not built | F83: Nice to Have | G83: In Progress | H83: No | I83: Not Tested | J83: 3284 | K83: Partially delivered: cover page and auto table of contents built by the Open Box house-style export (70a941a, fa6d8fb); cover client name added 2026-09-14 (d349d98). Executive summary is the only outstanding element. Story 3284 under Feature 3213 (Word & PDF Export).
A84: 80 | B84: Mapping / Coverage View | C84: Progress dashboard | D84: In-app view showing discovery completion (% scoped, % mapped, % enriched) per module. | E84: — not yet implemented | F84: Nice to Have | G84: Not Started | H84: N/A | I84: Not Tested | J84: 3285 | K84: Future enhancement. Story 3285 under Feature 3204 (Coverage Mapping Matrix).
A85: 81 | B85: Edit Mode | C85: Attach evidence to processes | D85: Link screenshots, documents, or meeting notes to individual processes as supporting artefacts. | E85: — not yet implemented | F85: Nice to Have | G85: Not Started | H85: N/A | I85: Not Tested | J85: 3286 | K85: Future enhancement. Story 3286 under Feature 3210 (Edit Mode Content Authoring).
A86: 82 | B86: Versioning & Persistence | C86: Search / filter versions | D86: Allow users to search or filter the versions list by name so they can quickly locate a saved client version when the list is long. | E86: — not yet implemented | F86: Nice to Have | G86: Not Started | H86: N/A | I86: Not Tested | J86: 3287 | K86: Added 2026-08-18. Future enhancement — search/filter versions panel when version count grows.
A87: 83 | B87: Versioning & Persistence | C87: Discovery Baseline built-in version | D87: Default landing version for a new engagement: loads the full taxonomy and link set with every scope and coverage tag cleared, so discovery starts untagged. Read-only. | E87: main.js · loadVersion() / clearAllTags(); state.js · suppressAutoScope; versionMenu.js | F87: Existing | G87: Done | H87: No | I87: Not Tested | J87: — Feature "Discovery Baseline template" (no story id in export) | K87: App-only when identified 2026-09-09; the 2026-09-14 board export raised a matching Feature ("Discovery Baseline template"). Still has no user story beneath it.
A88: 84 | B88: Versioning & Persistence | C88: Built-in version edit lock | D88: Save Changes is hidden and overwrite is blocked while a built-in baseline (Original / Discovery Baseline) is active, so factory content cannot be overwritten. | E88: state.js · BUILTIN_VERSIONS; main.js · updateSaveChangesBtn() / saveChangesToVersion() | F88: Existing | G88: Done | H88: No | I88: Not Tested | J88: — none (story needed) | K88: App-only feature with no DevOps story — one should be raised. Identified 2026-09-09.
A89: 85 | B89: Document Export | C89: Client name on cover from version title | D89: The document cover and footer take the client name from the saved version title; the built-in baselines fall back to a "Client Name" placeholder. | E89: genModal.js · coverClientName(); docxExport.js · buildBrandedDocument() | F89: Existing | G89: Done | H89: Yes | I89: Pass | J89: — none (story needed) | K89: Added 2026-09-14 (commit d349d98). Verified by unzipping the generated .docx — the cover runs and footer1.xml both carry the version title. No DevOps story yet.
A90: 86 | B90: Versioning & Persistence | C90: Original factory content baseline version | D90: Restores every built-in module to factory content with its original scope and coverage tags and the full seeded link set — the fully-linked reference template, as distinct from the untagged Discovery Baseline. | E90: main.js · loadVersion('original'); data/index.js · ORIGINAL_DATA; links.js · seedLinks() | F90: DevOps Backlog | G90: Done | H90: No | I90: Not Tested | J90: — Feature "Fully linked Original Factory Content template" (no story id in export) | K90: Added from the 2026-09-14 board export, which raised this as a Feature. Built but had no tracker row and still has no user story beneath the feature.
A91: 87 | B91: Scope & Coverage Tagging | C91: Proposed Scope Tagging | D91: Lets Open Box record, on either side of the taxonomy, where discovery has identified potential value add beyond what the client does today — a flag orthogonal to the existing coverage/scope tags, so the current-state tag is preserved. | E91: src/components/proposalField.js, grid.js, businessView.js, genModal.js, docxExport.js; src/data/links.js | F91: DevOps Backlog | G91: Done | H91: No | I91: Ready for Testing | J91: 3350 | K91: Added 2026-10-01. DevOps Feature 3350. Implementation confirmed present by code inspection; core flow (propose a card, filter by Proposed Scope) smoke-tested in browser — no formal QA test pass run yet.
A92: 88 | B92: Scope & Coverage Tagging | C92: Flag a value-stream process as Proposed Scope | D92: A Propose control on each Value Streams card in Edit Mode; flagging it does not change the coverage tag; the card shows both tags together; saved with the version. | E92: src/components/proposalField.js, grid.js, businessView.js, genModal.js, docxExport.js; src/data/links.js | F92: DevOps Backlog | G92: Done | H92: No | I92: Ready for Testing | J92: 3352 | K92: Added 2026-10-01. DevOps User Story 3352. Implementation confirmed present by code inspection; core flow (propose a card, filter by Proposed Scope) smoke-tested in browser — no formal QA test pass run yet.
A93: 89 | B93: Scope & Coverage Tagging | C93: Flag an MRI PMX system process as Proposed Scope | D93: A Propose control on each System view card in Edit Mode; the existing scope tag (Core/Custom/Out of scope) is retained; saved with the version. | E93: src/components/proposalField.js, grid.js, businessView.js, genModal.js, docxExport.js; src/data/links.js | F93: DevOps Backlog | G93: Done | H93: No | I93: Ready for Testing | J93: 3353 | K93: Added 2026-10-01. DevOps User Story 3353. Implementation confirmed present by code inspection; core flow (propose a card, filter by Proposed Scope) smoke-tested in browser — no formal QA test pass run yet.
A94: 90 | B94: Scope & Coverage Tagging | C94: Capture the value-add rationale for a proposal | D94: Both edit modals expose a Proposed Scope checkbox and rationale field; the rationale appears in the detail panel and generated document; unticking clears it. | E94: src/components/proposalField.js, grid.js, businessView.js, genModal.js, docxExport.js; src/data/links.js | F94: DevOps Backlog | G94: Done | H94: No | I94: Ready for Testing | J94: 3354 | K94: Added 2026-10-01. DevOps User Story 3354. Implementation confirmed present by code inspection; core flow (propose a card, filter by Proposed Scope) smoke-tested in browser — no formal QA test pass run yet.
A95: 91 | B95: Scope & Coverage Tagging | C95: Distinguish a proposal from agreed client scope at a glance | D95: Proposals use a distinct marker and dashed treatment, differing by shape as well as colour for colour-blind legibility; the panel states the item is a recommendation, not agreed scope. | E95: src/components/proposalField.js, grid.js, businessView.js, genModal.js, docxExport.js; src/data/links.js | F95: DevOps Backlog | G95: Done | H95: No | I95: Ready for Testing | J95: 3355 | K95: Added 2026-10-01. DevOps User Story 3355. Implementation confirmed present by code inspection; core flow (propose a card, filter by Proposed Scope) smoke-tested in browser — no formal QA test pass run yet.
A96: 92 | B96: Scope & Coverage Tagging | C96: Style the Proposed Scope tag to the Open Box brand palette | D96: The ✦ PROPOSED chip and related badges use the Open Box brand colour (CSS var(--prop) / var(--prop-accent)). | E96: src/components/proposalField.js, grid.js, businessView.js, genModal.js, docxExport.js; src/data/links.js | F96: DevOps Backlog | G96: Done | H96: No | I96: Ready for Testing | J96: 3356 | K96: Added 2026-10-01. DevOps User Story 3356. Implementation confirmed present by code inspection; core flow (propose a card, filter by Proposed Scope) smoke-tested in browser — no formal QA test pass run yet.
A97: 93 | B97: Scope & Coverage Tagging | C97: Bulk-propose or clear proposals for a column | D97: The Tag all menu in both views offers Propose all / Clear proposals, applied to every process and sub-process in the column, leaving coverage/scope tags untouched; one undo step. | E97: src/components/proposalField.js, grid.js, businessView.js, genModal.js, docxExport.js; src/data/links.js | F97: DevOps Backlog | G97: Done | H97: No | I97: Ready for Testing | J97: 3351 | K97: Added 2026-10-01. DevOps User Story 3351. Implementation confirmed present by code inspection; core flow (propose a card, filter by Proposed Scope) smoke-tested in browser — no formal QA test pass run yet.
... A108: 104 | B108: Document Export | C108: Nest linked counterparts under each proposal | D108: Each proposal entry lists its linked counterparts as supporting detail, with proposed links marked as such in the list. | E108: src/components/proposalField.js, grid.js, businessView.js, genModal.js, docxExport.js; src/data/links.js | F108: DevOps Backlog | G108: Done | H108: No | I108: Ready for Testing | J108: 3367 | K108: Added 2026-10-01. DevOps User Story 3367. Implementation confirmed present by code inspection; core flow (propose a card, filter by Proposed Scope) smoke-tested in browser — no formal QA test pass run yet.

Sheet Comparison
A1: DevOps Backlog ⇄ App Feature Comparison
A2: Board export 2026-09-15: 60 user stories, 224 story points — 8 Pending Feedback, 22 Resolved, 1 Active, 1 Development, 9 Closed, 1 Testing, 4 Analysis, 14 New. 46 of 60 progressed beyond New; 99 of 224 pts Resolved/Closed. 2 stories still read "New" although the tracker records them built. 4 app features have no story (Feature List #83-#86).
A3: A · Matched — board story ↔ existing feature
A4: DevOps ID | B4: Story title | C4: MoSCoW | D4: Board state | E4: Pts | F4: Matched feature(s) | G4: Actual (in code) | H4: Notes / discrepancy
A5: 3216 | B5: Switch between the three engagement views | C5: Must | D5: Pending Feedback | E5: 3 | F5: Three top-level views | G5: Done (in code)
A6: 3217 | B6: Open a detail panel for any card | C6: Must | D6: Resolved | E6: 2 | F6: Detail panel; Core activities & overview | G6: Done (in code)
A7: 3218 | B7: Browse the Tab-Column-Card hierarchy | C7: Must | D7: Pending Feedback | E7: 2 | F7: Process/sub card grid; Module tab bar | G7: Done (in code)
A8: 3219 | B8: Expand and collapse sub-processes | C8: Should | D8: Development | E8: 3 | F8: Expand / collapse sub-processes | G8: Done (in code)
A9: 3221 | B9: Browse CRE value streams | C9: Must | D9: Resolved | E9: 3 | F9: CRE value-stream taxonomy; Value-stream tab bar | G9: Done (in code)
A10: 3222 | B10: See which cards still need enrichment | C10: Should | D10: Analysis | E10: 2 | F10: Enrichment flag | G10: Done (in code)
A11: 3223 | B11: View market variation for a process | C11: Should | D11: Analysis | E11: 3 | F11: Market variation detail | G11: Done (in code)
A12: 3224 | B12: View vertical/sector detail for a process | C12: Should | D12: Pending Feedback | E12: 3 | F12: Vertical / sector detail | G12: Done (in code)
A13: 3225 | B13: See standards and frameworks on a process | C13: Could | D13: Pending Feedback | E13: 2 | F13: Standards & frameworks chips | G13: Done (in code)
A14: 3226 | B14: Filter value streams by market | C14: Should | D14: Pending Feedback | E14: 2 | F14: Market filter | G14: Done (in code)
A15: 3227 | B15: Filter value streams by vertical | C15: Should | D15: Pending Feedback | E15: 2 | F15: Vertical filter | G15: Done (in code)
A16: 3228 | B16: Browse the MRI PMX system taxonomy | C16: Must | D16: Resolved | E16: 3 | F16: Process/sub card grid; 9 built-in MRI modules | G16: Done (in code)
A17: 3229 | B17: See MRI setup detail for a system process | C17: Must | D17: Resolved | E17: 3 | F17: MRI module reference; Setup prerequisites; Associated screens | G17: Done (in code)
A18: 3231 | B18: See linked counterparts in both directions | C18: Must | D18: Closed | E18: 3 | F18: Panel cross-references | G18: Done (in code) | H18: Board Closed as at 2026-09-15; implemented in code.
A19: 3232 | B19: Navigate to a linked counterpart | C19: Must | D19: Closed | E19: 3 | F19: Click-through navigation | G19: Done (in code) | H19: Board Closed as at 2026-09-15; implemented in code.
A20: 3233 | B20: Add a link in Edit Mode | C20: Must | D20: Closed | E20: 5 | F20: Inline link editor; Add-link drill-down combobox | G20: Done (in code) | H20: Board Closed as at 2026-09-15; implemented in code.
A21: 3234 | B21: Remove a link in Edit Mode | C21: Must | D21: Closed | E21: 3 | F21: Inline link editor (remove) | G21: Done (in code) | H21: Board Closed as at 2026-09-15; implemented in code.
A22: 3235 | B22: View the coverage mapping matrix | C22: Should | D22: Resolved | E22: 5 | F22: Coverage matrix; Coverage colour coding | G22: Done (in code)
A23: 3236 | B23: Drill into a matrix cell | C23: Should | D23: Closed | E23: 3 | F23: Cell detail (visual flow) | G23: Done (in code)
A24: 3237 | B24: Identify coverage gaps | C24: Should | D24: Resolved | E24: 3 | F24: Gap highlighting | G24: Done (in code)
A25: 3238 | B25: Tag a value-stream process with system coverage | C25: Must | D25: Resolved | E25: 3 | F25: Coverage tags (Business) | G25: Done (in code)
A26: 3239 | B26: See context for a coverage tag on hover | C26: Should | D26: New | E26: 2 | F26: Coverage colour coding (coverageTooltip) | G26: Done (in code) | H26: Tooltip exists in code (coverageTooltip); feature #26 Done. Board still New as at 2026-09-15 — needs moving.
A27: 3240 | B27: Be warned when a covered process is unlinked | C27: Must | D27: Resolved | E27: 3 | F27: Missing-link warning | G27: Done (in code)
A28: 3241 | B28: Filter value streams by system coverage | C28: Should | D28: Resolved | E28: 3 | F28: System-coverage filter | G28: Done (in code)
A29: 3242 | B29: Bulk-tag a column's coverage | C29: Could | D29: Resolved | E29: 3 | F29: Coverage tags (Business) — bulk per domain | G29: Done (in code)
A30: 3243 | B30: Tag a system process's scope | C30: Should | D30: Pending Feedback | E30: 3 | F30: Scope tags (System) | G30: Done (in code)
A31: 3244 | B31: Auto-derive out-of-scope for unlinked processes | C31: Should | D31: New | E31: 5 | F31: Auto out-of-scope | G31: Done (in code) | H31: Feature #37 Done (grid.js · effectiveScope). Board still New as at 2026-09-15 — needs moving.
A32: 3245 | B32: Bulk-tag a system column's scope | C32: Could | D32: Resolved | E32: 3 | F32: Bulk-tag column scope | G32: Done (in code)
A33: 3246 | B33: Filter the system view by scope | C33: Should | D33: Resolved | E33: 3 | F33: Scope filter (System) | G33: Done (in code)
A34: 3247 | B34: Add, edit and remove business items | C34: Must | D34: Resolved | E34: 5 | F34: Add / Edit / Remove items (business) | G34: Done (in code)
A35: 3248 | B35: Add, edit and remove system items | C35: Must | D35: Analysis | E35: 5 | F35: Add / Edit / Remove items (system) | G35: Done (in code)
A36: 3249 | B36: Capture a client note on an item | C36: Should | D36: Resolved | E36: 3 | F36: Client notes | G36: Done (in code)
A37: 3250 | B37: Save a named client version | C37: Must | D37: Resolved | E37: 5 | F37: Save named versions; Full-state snapshots | G37: Done (in code)
A38: 3251 | B38: Load, rename and delete versions | C38: Must | D38: Closed | E38: 3 | F38: Load / rename / delete versions | G38: Done (in code)
A39: 3252 | B39: Undo recent changes | C39: Should | D39: Resolved | E39: 3 | F39: Undo (up to 20 steps) | G39: Done (in code)
A40: 3253 | B40: Reset to original content | C40: Could | D40: Resolved | E40: 2 | F40: Reset current tab; Reset all | G40: Done (in code)
A41: 3254 | B41: Toggle module and stream visibility | C41: Could | D41: Resolved | E41: 3 | F41: Per-module visibility; Visibility saved per version | G41: Partially built | H41: PARTIAL: module visibility built (#54-#56); per-stream (value-stream) visibility never implemented. Board Resolved as at 2026-09-15 — query whether the story was closed on partial delivery.
A42: 3255 | B42: Export to Word | C42: Should | D42: Resolved | E42: 5 | F42: Word export; Scope summary; Business document mode | G42: Done (in code)
A43: 3256 | B43: Export to PDF | C43: Should | D43: Resolved | E43: 3 | F43: PDF export (print) | G43: Done (in code)
A45: B · On board only — not in the app baseline (add / assess)
A46: DevOps ID | B46: Story title | C46: MoSCoW | D46: Board state | E46: Pts | F46: Actual (in code) | G46: Action / note
A47: 3220 | B47: Scroll a long tab bar | C47: Could | D47: Closed | E47: 2 | F47: Done (in code) | G47: Implemented via CSS overflow; added to Feature List. Board Closed as at 2026-09-15 — reconciled.
A48: 3230 | B48: See placeholder modules flagged | C48: Could | D48: New | E48: 2 | F48: Not built | G48: GAP — no in-app flag on placeholder modules; only SME-review code comments. Added to Feature List as Not Started.
A49: 3257 | B49: Select the target ERP | C49: Won't | D49: New | E49: 8 | F49: Not built | G49: Future / multi-ERP. Single ALL_DATA today. Added to Feature List as Not Started.
A50: 3258 | B50: Share a client version between users | C50: Won't | D50: New | E50: 5 | F50: Not built | G50: Future export/import. Confirmed absent (CLAUDE.md). Added to Feature List as Not Started.
A52: C · Previously app-only — now have DevOps stories
A53: Feature | B53: Category | C53: Where it lives | D53: Note
A54: View-specific hints | B54: Views & Navigation | C54: main.js · VIEW_HINTS | D54: Story 3278 created. Board Pending Feedback as at 2026-09-15.
A55: Keyboard shortcuts | B55: Views & Navigation | C55: main.js · keydown handler | D55: Story 3279 created. Board Testing as at 2026-09-15.
A56: Add custom module tab | B56: Edit Mode | C56: addModal.js · confirmAddTab() | D56: Story 3276 created. Board Analysis as at 2026-09-15.
A57: Save changes to active version | B57: Versioning & Persistence | C57: main.js · saveChangesToVersion() | D57: Story 3277 created. Board Resolved as at 2026-09-15.
A58: Version badge + dirty indicator | B58: Versioning & Persistence | C58: main.js · updateVersionBadge() | D58: Story 3280 created. Board Resolved as at 2026-09-15.
A60: D · New requirements — added to DevOps board
A61: Feature | B61: Category | C61: Description | D61: Suggested story title | E61: Dev Status | F61: Action
A62: Value-stream naming conventions with descriptions | B62: Business Process View | C62: Ensure each value stream has a clear, standardised naming convention with a description of its scope and purpose. | D62: Standardise value-stream names and descriptions | E62: Closed | F62: Added: Story 3270
A63: Cross-market value-stream validation (US / UK) | B63: Business Process View | C63: Confirm that value-stream names are meaningful for both US and UK markets (e.g. "Recoveries" vs "Service Charges") and reconcile terminology. | D63: Validate value-stream naming across US/UK markets | E63: New | F63: Added: Story 3271
A64: Tagging methodology review and taxonomy alignment | B64: Scope & Coverage Tagging | C64: Review scope/coverage tagging approach and confirm whether tags should align with the existing taxonomy structure. | D64: Review and align tagging methodology | E64: New | F64: Added: Story 3272
A65: Security features and responsibility boundaries | B65: Security & Access Control | C65: Define who can edit the master copy, whether access grants editing rights, and responsibility boundaries between roles. | D65: Define security model and access control | E65: New | F65: Added: Story 3273
A66: Database persistence (replace localStorage) | B66: Versioning & Persistence | C66: Move data from browser localStorage to a database so it persists across browsers, machines, and users. | D66: Add database backend for persistence | E66: New | F66: Added: Story 3274
A68: E · Nice to have — on the board, not in the delivered baseline
A69: DevOps ID | B69: Story title | C69: MoSCoW | D69: Board state | E69: Pts | F69: Actual (in code) | G69: Action / note
A70: 3281 | B70: Version comparison (side-by-side diff) | C70: Could | D70: New | E70: 8 | F70: Not built | G70: Future enhancement. Feature List #76.
A71: 3282 | B71: Guided discovery workflow | C71: Could | D71: Active | E71: 13 | F71: Not built | G71: Future enhancement. Feature List #77.
A72: 3283 | B72: Duplicate a version | C72: Could | D72: Closed | E72: 3 | F72: Done (in code) | G72: Built: versionMenu.js · startDuplicate(). Feature List #78.
A73: 3284 | B73: Richer export templates | C73: Could | D73: New | E73: 8 | F73: Partially built | G73: Cover page + TOC built; executive summary outstanding. Feature List #79.
A74: 3285 | B74: Progress dashboard | C74: Could | D74: New | E74: 8 | F74: Not built | G74: Future enhancement. Feature List #80.
A75: 3286 | B75: Attach evidence to processes | C75: Could | D75: New | E75: 8 | F75: Not built | G75: Future enhancement. Feature List #81.
A76: 3287 | B76: Search / filter versions | C76: Could | D76: New | E76: — | F76: Not built | G76: Future enhancement. Feature List #82.

Sheet Summary
A1: Feature & QA Summary
A3: Development Status
A4: Dev Status | B4: Count | C4: % of total
A5: Done | B5: =COUNTIF('Feature List'!$G$5:$G$200,"Done") | C5: =IF(COUNTA('Feature List'!$G$5:$G$200)=0,0,COUNTIF('Feature List'!$G$5:$G$200,"Done")/COUNTA('Feature List'!$G$5:$G$200))
A6: In Progress | B6: =COUNTIF('Feature List'!$G$5:$G$200,"In Progress") | C6: =IF(COUNTA('Feature List'!$G$5:$G$200)=0,0,COUNTIF('Feature List'!$G$5:$G$200,"In Progress")/COUNTA('Feature List'!$G$5:$G$200))
A7: Not Started | B7: =COUNTIF('Feature List'!$G$5:$G$200,"Not Started") | C7: =IF(COUNTA('Feature List'!$G$5:$G$200)=0,0,COUNTIF('Feature List'!$G$5:$G$200,"Not Started")/COUNTA('Feature List'!$G$5:$G$200))
A8: Backlog | B8: =COUNTIF('Feature List'!$G$5:$G$200,"Backlog") | C8: =IF(COUNTA('Feature List'!$G$5:$G$200)=0,0,COUNTIF('Feature List'!$G$5:$G$200,"Backlog")/COUNTA('Feature List'!$G$5:$G$200))
A9: Blocked | B9: =COUNTIF('Feature List'!$G$5:$G$200,"Blocked") | C9: =IF(COUNTA('Feature List'!$G$5:$G$200)=0,0,COUNTIF('Feature List'!$G$5:$G$200,"Blocked")/COUNTA('Feature List'!$G$5:$G$200))
A10: Total | B10: =COUNTA('Feature List'!$G$5:$G$200) | C10: =IF(COUNTA('Feature List'!$G$5:$G$200)=0,0,1)
A12: QA Status
A13: QA Status | B13: Count | C13: % of total
A14: Not Tested | B14: =COUNTIF('Feature List'!$I$5:$I$200,"Not Tested") | C14: =IF(COUNTA('Feature List'!$I$5:$I$200)=0,0,COUNTIF('Feature List'!$I$5:$I$200,"Not Tested")/COUNTA('Feature List'!$I$5:$I$200))
A15: In Progress | B15: =COUNTIF('Feature List'!$I$5:$I$200,"In Progress") | C15: =IF(COUNTA('Feature List'!$I$5:$I$200)=0,0,COUNTIF('Feature List'!$I$5:$I$200,"In Progress")/COUNTA('Feature List'!$I$5:$I$200))
A16: Pass | B16: =COUNTIF('Feature List'!$I$5:$I$200,"Pass") | C16: =IF(COUNTA('Feature List'!$I$5:$I$200)=0,0,COUNTIF('Feature List'!$I$5:$I$200,"Pass")/COUNTA('Feature List'!$I$5:$I$200))
A17: Failed | B17: =COUNTIF('Feature List'!$I$5:$I$200,"Failed") | C17: =IF(COUNTA('Feature List'!$I$5:$I$200)=0,0,COUNTIF('Feature List'!$I$5:$I$200,"Failed")/COUNTA('Feature List'!$I$5:$I$200))
A18: Blocked | B18: =COUNTIF('Feature List'!$I$5:$I$200,"Blocked") | C18: =IF(COUNTA('Feature List'!$I$5:$I$200)=0,0,COUNTIF('Feature List'!$I$5:$I$200,"Blocked")/COUNTA('Feature List'!$I$5:$I$200))
A19: Total | B19: =COUNTA('Feature List'!$I$5:$I$200) | C19: =IF(COUNTA('Feature List'!$I$5:$I$200)=0,0,1)
A21: Source
A22: Source | B22: Count | C22: % of total
A23: Existing | B23: =COUNTIF('Feature List'!$F$5:$F$200,"Existing") | C23: =IF(COUNTA('Feature List'!$F$5:$F$200)=0,0,COUNTIF('Feature List'!$F$5:$F$200,"Existing")/COUNTA('Feature List'!$F$5:$F$200))
A24: DevOps Backlog | B24: =COUNTIF('Feature List'!$F$5:$F$200,"DevOps Backlog") | C24: =IF(COUNTA('Feature List'!$F$5:$F$200)=0,0,COUNTIF('Feature List'!$F$5:$F$200,"DevOps Backlog")/COUNTA('Feature List'!$F$5:$F$200))
A25: New Requirement | B25: =COUNTIF('Feature List'!$F$5:$F$200,"New Requirement") | C25: =IF(COUNTA('Feature List'!$F$5:$F$200)=0,0,COUNTIF('Feature List'!$F$5:$F$200,"New Requirement")/COUNTA('Feature List'!$F$5:$F$200))
A26: Nice to Have | B26: =COUNTIF('Feature List'!$F$5:$F$200,"Nice to Have") | C26: =IF(COUNTA('Feature List'!$F$5:$F$200)=0,0,COUNTIF('Feature List'!$F$5:$F$200,"Nice to Have")/COUNTA('Feature List'!$F$5:$F$200))
A27: Total | B27: =COUNTA('Feature List'!$F$5:$F$200) | C27: =IF(COUNTA('Feature List'!$F$5:$F$200)=0,0,1)
A28: Backlog Comparison
A29: Board stories total | B29: 60
A30: Matched to a tracker feature | B30: 60
A31: On board only (section B) | B31: 4
A32: In app only (no story) | B32: 4
A33: New requirements still to raise | B33: 0
A34: Board "New" but built in code | B34: 2

Sheet Status Key
A1: Status Key — allowed values
A3: Column | B3: Allowed values & meaning
A4: Source | B4: Existing = already in the app (source-derived baseline). DevOps Backlog = folded in from the board. New Requirement = raised during review. Nice to Have = future enhancement.
A5: Dev Status | B5: Done = built in the codebase. In Progress = under active development (board Active/Development, or partially built). Not Started / Backlog = planned only. Blocked = cannot proceed.
A6: Tested? | B6: Yes = QA complete. No = not yet tested. Partial = some testing done. N/A = no QA needed.
A7: QA Status | B7: Not Tested · In Progress · Pass · Failed · Blocked — the outcome/progress of QA.
A8: DevOps Ref | B8: Matched Azure DevOps story ID(s). Multiple IDs = feature spans several stories.
A9: QA Notes | B9: Free text — discrepancies, defects, evidence links, tester, or context.
A10: Comparison sheet | B10: A = matched (board story ↔ feature); B = on board only; C = previously app-only, now has a story; D = new requirements added to the board; E = nice-to-have stories. "Actual (in code)" = what the source actually does, vs the board state. "Board state" and "Pts" come from the latest DevOps export (2026-09-15).
